<?xml version="1.0" encoding="UTF-8"?>
<GenRun Id="impl_1" LaunchPart="xc7z020clg400-2" LaunchTime="1651047084">
  <File Type="BITSTR-BMM" Name="sender_wrapper_bd.bmm"/>
  <File Type="OPT-METHODOLOGY-DRC" Name="sender_wrapper_methodology_drc_opted.rpt"/>
  <File Type="INIT-TIMING" Name="sender_wrapper_timing_summary_init.rpt"/>
  <File Type="ROUTE-PWR" Name="sender_wrapper_power_routed.rpt"/>
  <File Type="PA-TCL" Name="sender_wrapper.tcl"/>
  <File Type="OPT-TIMING" Name="sender_wrapper_timing_summary_opted.rpt"/>
  <File Type="OPT-DCP" Name="sender_wrapper_opt.dcp"/>
  <File Type="ROUTE-PWR-SUM" Name="sender_wrapper_power_summary_routed.pb"/>
  <File Type="REPORTS-TCL" Name="sender_wrapper_reports.tcl"/>
  <File Type="OPT-DRC" Name="sender_wrapper_drc_opted.rpt"/>
  <File Type="OPT-HWDEF" Name="sender_wrapper.hwdef"/>
  <File Type="PWROPT-DCP" Name="sender_wrapper_pwropt.dcp"/>
  <File Type="PWROPT-DRC" Name="sender_wrapper_drc_pwropted.rpt"/>
  <File Type="PWROPT-TIMING" Name="sender_wrapper_timing_summary_pwropted.rpt"/>
  <File Type="PLACE-DCP" Name="sender_wrapper_placed.dcp"/>
  <File Type="PLACE-IO" Name="sender_wrapper_io_placed.rpt"/>
  <File Type="PLACE-CLK" Name="sender_wrapper_clock_utilization_placed.rpt"/>
  <File Type="PLACE-UTIL" Name="sender_wrapper_utilization_placed.rpt"/>
  <File Type="PLACE-UTIL-PB" Name="sender_wrapper_utilization_placed.pb"/>
  <File Type="PLACE-CTRL" Name="sender_wrapper_control_sets_placed.rpt"/>
  <File Type="PLACE-SIMILARITY" Name="sender_wrapper_incremental_reuse_placed.rpt"/>
  <File Type="PLACE-PRE-SIMILARITY" Name="sender_wrapper_incremental_reuse_pre_placed.rpt"/>
  <File Type="BG-BGN" Name="sender_wrapper.bgn"/>
  <File Type="PLACE-TIMING" Name="sender_wrapper_timing_summary_placed.rpt"/>
  <File Type="POSTPLACE-PWROPT-DCP" Name="sender_wrapper_postplace_pwropt.dcp"/>
  <File Type="BG-BIN" Name="sender_wrapper.bin"/>
  <File Type="POSTPLACE-PWROPT-TIMING" Name="sender_wrapper_timing_summary_postplace_pwropted.rpt"/>
  <File Type="PHYSOPT-DCP" Name="sender_wrapper_physopt.dcp"/>
  <File Type="PHYSOPT-DRC" Name="sender_wrapper_drc_physopted.rpt"/>
  <File Type="BITSTR-MSK" Name="sender_wrapper.msk"/>
  <File Type="PHYSOPT-TIMING" Name="sender_wrapper_timing_summary_physopted.rpt"/>
  <File Type="ROUTE-ERROR-DCP" Name="sender_wrapper_routed_error.dcp"/>
  <File Type="ROUTE-DCP" Name="sender_wrapper_routed.dcp"/>
  <File Type="ROUTE-BLACKBOX-DCP" Name="sender_wrapper_routed_bb.dcp"/>
  <File Type="ROUTE-DRC" Name="sender_wrapper_drc_routed.rpt"/>
  <File Type="ROUTE-DRC-PB" Name="sender_wrapper_drc_routed.pb"/>
  <File Type="BITSTR-LTX" Name="debug_nets.ltx"/>
  <File Type="BITSTR-LTX" Name="sender_wrapper.ltx"/>
  <File Type="ROUTE-DRC-RPX" Name="sender_wrapper_drc_routed.rpx"/>
  <File Type="BITSTR-MMI" Name="sender_wrapper.mmi"/>
  <File Type="ROUTE-METHODOLOGY-DRC" Name="sender_wrapper_methodology_drc_routed.rpt"/>
  <File Type="ROUTE-METHODOLOGY-DRC-RPX" Name="sender_wrapper_methodology_drc_routed.rpx"/>
  <File Type="BITSTR-SYSDEF" Name="sender_wrapper.sysdef"/>
  <File Type="ROUTE-METHODOLOGY-DRC-PB" Name="sender_wrapper_methodology_drc_routed.pb"/>
  <File Type="ROUTE-PWR-RPX" Name="sender_wrapper_power_routed.rpx"/>
  <File Type="ROUTE-STATUS" Name="sender_wrapper_route_status.rpt"/>
  <File Type="ROUTE-STATUS-PB" Name="sender_wrapper_route_status.pb"/>
  <File Type="ROUTE-TIMINGSUMMARY" Name="sender_wrapper_timing_summary_routed.rpt"/>
  <File Type="ROUTE-TIMING-PB" Name="sender_wrapper_timing_summary_routed.pb"/>
  <File Type="ROUTE-TIMING-RPX" Name="sender_wrapper_timing_summary_routed.rpx"/>
  <File Type="ROUTE-SIMILARITY" Name="sender_wrapper_incremental_reuse_routed.rpt"/>
  <File Type="ROUTE-CLK" Name="sender_wrapper_clock_utilization_routed.rpt"/>
  <File Type="ROUTE-BUS-SKEW" Name="sender_wrapper_bus_skew_routed.rpt"/>
  <File Type="ROUTE-BUS-SKEW-PB" Name="sender_wrapper_bus_skew_routed.pb"/>
  <File Type="ROUTE-BUS-SKEW-RPX" Name="sender_wrapper_bus_skew_routed.rpx"/>
  <File Type="POSTROUTE-PHYSOPT-DCP" Name="sender_wrapper_postroute_physopt.dcp"/>
  <File Type="POSTROUTE-PHYSOPT-BLACKBOX-DCP" Name="sender_wrapper_postroute_physopt_bb.dcp"/>
  <File Type="POSTROUTE-PHYSOPT-TIMING" Name="sender_wrapper_timing_summary_postroute_physopted.rpt"/>
  <File Type="POSTROUTE-PHYSOPT-TIMING-PB" Name="sender_wrapper_timing_summary_postroute_physopted.pb"/>
  <File Type="POSTROUTE-PHYSOPT-TIMING-RPX" Name="sender_wrapper_timing_summary_postroute_physopted.rpx"/>
  <File Type="POSTROUTE-PHYSOPT-BUS-SKEW" Name="sender_wrapper_bus_skew_postroute_physopted.rpt"/>
  <File Type="POSTROUTE-PHYSOPT-BUS-SKEW-PB" Name="sender_wrapper_bus_skew_postroute_physopted.pb"/>
  <File Type="BG-BIT" Name="sender_wrapper.bit"/>
  <File Type="POSTROUTE-PHYSOPT-BUS-SKEW-RPX" Name="sender_wrapper_bus_skew_postroute_physopted.rpx"/>
  <File Type="BITSTR-RBT" Name="sender_wrapper.rbt"/>
  <File Type="BITSTR-NKY" Name="sender_wrapper.nky"/>
  <File Type="BG-DRC" Name="sender_wrapper.drc"/>
  <File Type="RDI-RDI" Name="sender_wrapper.vdi"/>
  <File Type="WBT-USG" Name="usage_statistics_webtalk.html"/>
  <FileSet Name="sources" Type="DesignSrcs" RelSrcDir="$PSRCDIR/sources_1">
    <Filter Type="Srcs"/>
    <File Path="$PSRCDIR/sources_1/imports/generated/DDC/DDCWrapper.v">
      <FileInfo>
        <Attr Name="ImportPath" Val="$PPRDIR/../chisel-test-project/generated/DDC/DDCWrapper.v"/>
        <Attr Name="ImportTime" Val="1642817200"/>
        <Attr Name="UsedIn" Val="synthesis"/>
        <Attr Name="UsedIn" Val="implementation"/>
        <Attr Name="UsedIn" Val="simulation"/>
      </FileInfo>
    </File>
    <File Path="$PSRCDIR/sources_1/imports/srcs/mux.v">
      <FileInfo>
        <Attr Name="ImportPath" Val="$PPRDIR/srcs/mux.v"/>
        <Attr Name="ImportTime" Val="1642899268"/>
        <Attr Name="UsedIn" Val="synthesis"/>
        <Attr Name="UsedIn" Val="implementation"/>
        <Attr Name="UsedIn" Val="simulation"/>
      </FileInfo>
    </File>
    <File Path="$PSRCDIR/sources_1/imports/generated/DUC/DUCWrapper.v">
      <FileInfo>
        <Attr Name="ImportPath" Val="$PPRDIR/../chisel-test-project/generated/DUC/DUCWrapper.v"/>
        <Attr Name="ImportTime" Val="1642817200"/>
        <Attr Name="UsedIn" Val="synthesis"/>
        <Attr Name="UsedIn" Val="implementation"/>
        <Attr Name="UsedIn" Val="simulation"/>
      </FileInfo>
    </File>
    <File Path="$PSRCDIR/sources_1/imports/srcs/adc_axis.v">
      <FileInfo>
        <Attr Name="UsedIn" Val="synthesis"/>
        <Attr Name="UsedIn" Val="implementation"/>
        <Attr Name="UsedIn" Val="simulation"/>
      </FileInfo>
    </File>
    <File Path="$PSRCDIR/sources_1/imports/srcs/dac_axis.v">
      <FileInfo>
        <Attr Name="UsedIn" Val="synthesis"/>
        <Attr Name="UsedIn" Val="implementation"/>
        <Attr Name="UsedIn" Val="simulation"/>
      </FileInfo>
    </File>
    <File Path="$PSRCDIR/sources_1/bd/urllc_fifo_core/urllc_fifo_core.bd">
      <FileInfo>
        <Attr Name="UsedIn" Val="synthesis"/>
        <Attr Name="UsedIn" Val="implementation"/>
        <Attr Name="UsedIn" Val="simulation"/>
      </FileInfo>
    </File>
    <File Path="$PSRCDIR/sources_1/new/sender_wrapper.v">
      <FileInfo>
        <Attr Name="UsedIn" Val="synthesis"/>
        <Attr Name="UsedIn" Val="implementation"/>
        <Attr Name="UsedIn" Val="simulation"/>
      </FileInfo>
    </File>
    <File Path="$PSRCDIR/sources_1/imports/srcs/axis_write_to_fifo.v">
      <FileInfo>
        <Attr Name="AutoDisabled" Val="1"/>
        <Attr Name="ImportPath" Val="$PPRDIR/srcs/axis_write_to_fifo.v"/>
        <Attr Name="ImportTime" Val="1642899268"/>
        <Attr Name="UsedIn" Val="synthesis"/>
        <Attr Name="UsedIn" Val="implementation"/>
        <Attr Name="UsedIn" Val="simulation"/>
      </FileInfo>
    </File>
    <File Path="$PSRCDIR/sources_1/imports/srcs/dac.v">
      <FileInfo>
        <Attr Name="AutoDisabled" Val="1"/>
        <Attr Name="ImportPath" Val="$PPRDIR/srcs/dac.v"/>
        <Attr Name="ImportTime" Val="1642899268"/>
        <Attr Name="UsedIn" Val="synthesis"/>
        <Attr Name="UsedIn" Val="implementation"/>
        <Attr Name="UsedIn" Val="simulation"/>
      </FileInfo>
    </File>
    <File Path="$PSRCDIR/sources_1/imports/srcs/adc.v">
      <FileInfo>
        <Attr Name="AutoDisabled" Val="1"/>
        <Attr Name="ImportPath" Val="$PPRDIR/srcs/adc.v"/>
        <Attr Name="ImportTime" Val="1642899268"/>
        <Attr Name="UsedIn" Val="synthesis"/>
        <Attr Name="UsedIn" Val="implementation"/>
        <Attr Name="UsedIn" Val="simulation"/>
      </FileInfo>
    </File>
    <File Path="$PSRCDIR/sources_1/imports/srcs/count_trigger.v">
      <FileInfo>
        <Attr Name="AutoDisabled" Val="1"/>
        <Attr Name="ImportPath" Val="$PPRDIR/srcs/count_trigger.v"/>
        <Attr Name="ImportTime" Val="1642899268"/>
        <Attr Name="UsedIn" Val="synthesis"/>
        <Attr Name="UsedIn" Val="implementation"/>
        <Attr Name="UsedIn" Val="simulation"/>
      </FileInfo>
    </File>
    <File Path="$PSRCDIR/sources_1/imports/srcs/fifo_read_to_axis.v">
      <FileInfo>
        <Attr Name="AutoDisabled" Val="1"/>
        <Attr Name="ImportPath" Val="$PPRDIR/srcs/fifo_read_to_axis.v"/>
        <Attr Name="ImportTime" Val="1642899268"/>
        <Attr Name="UsedIn" Val="synthesis"/>
        <Attr Name="UsedIn" Val="implementation"/>
        <Attr Name="UsedIn" Val="simulation"/>
      </FileInfo>
    </File>
    <File Path="$PSRCDIR/sources_1/bd/test_fifo_axis/test_fifo_axis.bd">
      <FileInfo>
        <Attr Name="AutoDisabled" Val="1"/>
        <Attr Name="UsedIn" Val="synthesis"/>
        <Attr Name="UsedIn" Val="implementation"/>
        <Attr Name="UsedIn" Val="simulation"/>
      </FileInfo>
    </File>
    <File Path="$PSRCDIR/sources_1/bd/test_fifo_axis/hdl/test_fifo_axis_wrapper.v">
      <FileInfo>
        <Attr Name="AutoDisabled" Val="1"/>
        <Attr Name="UsedIn" Val="synthesis"/>
        <Attr Name="UsedIn" Val="implementation"/>
        <Attr Name="UsedIn" Val="simulation"/>
      </FileInfo>
    </File>
    <Config>
      <Option Name="DesignMode" Val="RTL"/>
      <Option Name="TopModule" Val="sender_wrapper"/>
    </Config>
  </FileSet>
  <FileSet Name="constrs_in" Type="Constrs" RelSrcDir="$PSRCDIR/constrs_1">
    <Filter Type="Constrs"/>
    <File Path="$PSRCDIR/constrs_1/imports/srcs/urllc.xdc">
      <FileInfo>
        <Attr Name="ImportPath" Val="$PPRDIR/srcs/urllc.xdc"/>
        <Attr Name="ImportTime" Val="1643401474"/>
        <Attr Name="UsedIn" Val="synthesis"/>
        <Attr Name="UsedIn" Val="implementation"/>
      </FileInfo>
    </File>
    <Config>
      <Option Name="ConstrsType" Val="XDC"/>
    </Config>
  </FileSet>
  <FileSet Name="utils" Type="Utils" RelSrcDir="$PSRCDIR/utils_1">
    <Filter Type="Utils"/>
    <Config>
      <Option Name="TopAutoSet" Val="TRUE"/>
    </Config>
  </FileSet>
  <Strategy Version="1" Minor="2">
    <StratHandle Name="Vivado Implementation Defaults" Flow="Vivado Implementation 2018"/>
    <Step Id="init_design"/>
    <Step Id="opt_design"/>
    <Step Id="power_opt_design"/>
    <Step Id="place_design"/>
    <Step Id="post_place_power_opt_design"/>
    <Step Id="phys_opt_design"/>
    <Step Id="route_design"/>
    <Step Id="post_route_phys_opt_design"/>
    <Step Id="write_bitstream"/>
  </Strategy>
  <BlockFileSet Type="BlockSrcs" Name="urllc_fifo_core_clk_dynamic_0"/>
  <BlockFileSet Type="BlockSrcs" Name="urllc_fifo_core_reset_static_0"/>
  <BlockFileSet Type="BlockSrcs" Name="urllc_fifo_core_DUCWrapper_0_0"/>
  <BlockFileSet Type="BlockSrcs" Name="urllc_fifo_core_mux_reciever_in_0"/>
  <BlockFileSet Type="BlockSrcs" Name="urllc_fifo_core_DDCWrapper_0_0"/>
  <BlockFileSet Type="BlockSrcs" Name="urllc_fifo_core_axi_dma_0_0"/>
  <BlockFileSet Type="BlockSrcs" Name="urllc_fifo_core_reset_dynamic_0"/>
  <BlockFileSet Type="BlockSrcs" Name="urllc_fifo_core_clk_static_0"/>
  <BlockFileSet Type="BlockSrcs" Name="urllc_fifo_core_processing_system7_0_0"/>
  <BlockFileSet Type="BlockSrcs" Name="urllc_fifo_core_xbar_0"/>
  <BlockFileSet Type="BlockSrcs" Name="urllc_fifo_core_axi_gpio_0_0"/>
  <BlockFileSet Type="BlockSrcs" Name="urllc_fifo_core_mux_reciever_out_0"/>
  <BlockFileSet Type="BlockSrcs" Name="urllc_fifo_core_system_ila_0_0"/>
  <BlockFileSet Type="BlockSrcs" Name="urllc_fifo_core_xbar_1"/>
  <BlockFileSet Type="BlockSrcs" Name="urllc_fifo_core_adc_axis_0_0"/>
  <BlockFileSet Type="BlockSrcs" Name="urllc_fifo_core_axis_data_fifo_0_0"/>
  <BlockFileSet Type="BlockSrcs" Name="urllc_fifo_core_axis_data_fifo_adc_1"/>
  <BlockFileSet Type="BlockSrcs" Name="urllc_fifo_core_mux_adc_fifo_reset_0"/>
  <BlockFileSet Type="BlockSrcs" Name="urllc_fifo_core_mux_dac_fifo_reset_0"/>
  <BlockFileSet Type="BlockSrcs" Name="urllc_fifo_core_dac_axis_0_0"/>
</GenRun>
